{
  "_class": "group",
  "booleanOperation": -1,
  "clippingMaskMode": 0,
  "do_objectID": "5D760D24-C9EC-4A76-A2F3-0789C210A175",
  "exportOptions": {
    "_class": "exportOptions",
    "do_objectID": "F925C4C7-C010-4920-8F47-81A453F35C07",
    "exportFormats": [
    ],
    "includedLayerIds": [
    ],
    "layerOptions": 0,
    "shouldTrim": false
  },
  "frame": {
    "_class": "rect",
    "constrainProportions": false,
    "do_objectID": "E3FBCE12-FCE2-4F63-A8D3-049DC2836909",
    "height": 35,
    "width": 172,
    "x": 1150,
    "y": 47
  },
  "groupLayout": {
    "_class": "MSImmutableFreeformGroupLayout",
    "do_objectID": "BBA86E6A-6542-4DBE-9A46-E7D8E5CF7863"
  },
  "hasClickThrough": false,
  "hasClippingMask": false,
  "isFixedToViewport": false,
  "isFlippedHorizontal": false,
  "isFlippedVertical": false,
  "isLocked": false,
  "isVisible": true,
  "layerListExpandedType": 0,
  "layers": [
    {
      "class": "group",
      "id": "CA7CF228-1E30-440D-AF7E-FBCA189C9921"
    },
    {
      "class": "group",
      "id": "B20F46CD-3CAC-4BBD-9952-AD1B1AA44A5B"
    },
    {
      "class": "group",
      "id": "E4F9D7FC-71B0-41E7-A62A-0CBBADF96C3B"
    }
  ],
  "name": "Group 22",
  "nameIsFixed": false,
  "resizingConstraint": 63,
  "resizingType": 0,
  "rotation": 0,
  "shouldBreakMaskChain": false,
  "style": {
    "_class": "style",
    "do_objectID": "EB2E8F9D-7B01-4360-A9D5-ABC212CC6523",
    "endMarkerType": 0,
    "miterLimit": 10,
    "startMarkerType": 0,
    "windingRule": 1
  }
}