{
  "_class": "shapeGroup",
  "booleanOperation": -1,
  "clippingMaskMode": 0,
  "do_objectID": "056C3F39-DD01-4C36-9464-7A1CDD336175",
  "exportOptions": {
    "_class": "exportOptions",
    "do_objectID": "2B19D12B-F021-454B-A7C7-E355E1B020AE",
    "exportFormats": [
    ],
    "includedLayerIds": [
    ],
    "layerOptions": 0,
    "shouldTrim": false
  },
  "frame": {
    "_class": "rect",
    "constrainProportions": false,
    "do_objectID": "F4711598-8CD7-416E-B85E-001615538512",
    "height": 23.18125124173093,
    "width": 24.81100525168035,
    "x": 0.438500000000003,
    "y": 0.818948758269066
  },
  "groupLayout": {
    "_class": "MSImmutableFreeformGroupLayout",
    "do_objectID": "6D171A74-3F01-447F-9EE8-7AA2A29A1048"
  },
  "hasClickThrough": false,
  "hasClippingMask": false,
  "isFixedToViewport": false,
  "isFlippedHorizontal": false,
  "isFlippedVertical": false,
  "isLocked": false,
  "isVisible": true,
  "layerListExpandedType": 2,
  "layers": [
    {
      "class": "shapePath",
      "id": "45987C92-C2BE-41FE-9068-CA152322C5BB"
    },
    {
      "class": "shapePath",
      "id": "C21034D8-683C-4E1D-9BF0-CF33DF9F7890"
    },
    {
      "class": "shapePath",
      "id": "8605F35A-3CB4-4ABF-85B0-4695BA6EC112"
    },
    {
      "class": "shapePath",
      "id": "0B47048D-C168-485E-86AF-162B2610267D"
    },
    {
      "class": "shapePath",
      "id": "98CB4D38-0847-4D94-8694-9C238C5404E0"
    },
    {
      "class": "shapePath",
      "id": "6CCE27D3-F34B-48B1-8366-7CA1B6FA16AF"
    },
    {
      "class": "shapePath",
      "id": "F9267F47-25ED-4BD1-8805-2E85C0012D57"
    },
    {
      "class": "shapePath",
      "id": "85D23E75-B867-433B-B02F-54F68DE3FAEB"
    }
  ],
  "name": "Fill 1",
  "nameIsFixed": false,
  "resizingConstraint": 63,
  "resizingType": 0,
  "rotation": 0,
  "shouldBreakMaskChain": false,
  "style": {
    "_class": "style",
    "do_objectID": "39337597-3F0E-4FD5-8067-7F200BF1A3C3",
    "endMarkerType": 0,
    "fills": [
      {
        "_class": "fill",
        "color": {
          "_class": "color",
          "alpha": 0.8,
          "blue": 0.2509803921568627,
          "green": 0.2509803921568627,
          "red": 0.2509803921568627
        },
        "fillType": 0,
        "isEnabled": true,
        "noiseIndex": 0,
        "noiseIntensity": 0,
        "patternFillType": 1,
        "patternTileScale": 1
      }
    ],
    "miterLimit": 10,
    "startMarkerType": 0,
    "windingRule": 1
  },
  "windingRule": 1
}