{
  "_class": "group",
  "booleanOperation": -1,
  "clippingMaskMode": 0,
  "do_objectID": "16CF0DD9-138E-4F43-9E37-D1C52F14D317",
  "exportOptions": {
    "_class": "exportOptions",
    "do_objectID": "FD0345AB-34F5-4626-8F29-1BED504C1CA5",
    "exportFormats": [
    ],
    "includedLayerIds": [
    ],
    "layerOptions": 0,
    "shouldTrim": false
  },
  "frame": {
    "_class": "rect",
    "constrainProportions": false,
    "do_objectID": "54972B84-2F9D-4ADA-B379-D70D773C740B",
    "height": 16,
    "width": 60,
    "x": 0,
    "y": 0
  },
  "groupLayout": {
    "_class": "MSImmutableFreeformGroupLayout",
    "do_objectID": "7DDF2923-76D2-4FD4-A745-1987B49D1D73"
  },
  "hasClickThrough": false,
  "hasClippingMask": false,
  "isFixedToViewport": false,
  "isFlippedHorizontal": false,
  "isFlippedVertical": false,
  "isLocked": false,
  "isVisible": true,
  "layerListExpandedType": 2,
  "layers": [
    {
      "class": "text",
      "id": "404A89F1-D26F-44E0-8468-F3055BD08762"
    }
  ],
  "name": "Group Copy",
  "nameIsFixed": false,
  "resizingConstraint": 63,
  "resizingType": 0,
  "rotation": 0,
  "shouldBreakMaskChain": false,
  "style": {
    "_class": "style",
    "borderOptions": {
      "_class": "borderOptions",
      "dashPattern": [
      ],
      "do_objectID": "7DA26C57-DA85-47ED-ABE1-7130FC83F242",
      "isEnabled": true,
      "lineCapStyle": 0,
      "lineJoinStyle": 0
    },
    "colorControls": {
      "_class": "colorControls",
      "brightness": 0,
      "contrast": 1,
      "do_objectID": "AF13B361-99CA-4FCF-A6AF-C5E132A2F4AC",
      "hue": 0,
      "isEnabled": true,
      "saturation": 1
    },
    "do_objectID": "175B5A1D-50B2-4A13-AE9A-8E54FFE74050",
    "endMarkerType": 0,
    "miterLimit": 10,
    "startMarkerType": 0,
    "windingRule": 1
  }
}