{
  "_class": "symbolInstance",
  "booleanOperation": -1,
  "clippingMaskMode": 0,
  "do_objectID": "43EFCCC4-BA51-4340-A24B-E3F9ED61789D",
  "exportOptions": {
    "_class": "exportOptions",
    "do_objectID": "FBF2702C-9449-4515-8154-5BA79FBE042A",
    "exportFormats": [
    ],
    "includedLayerIds": [
    ],
    "layerOptions": 0,
    "shouldTrim": false
  },
  "frame": {
    "_class": "rect",
    "constrainProportions": false,
    "do_objectID": "0DEE3C17-596F-4E92-9845-2A6B689A3797",
    "height": 24,
    "width": 22,
    "x": 1,
    "y": 139
  },
  "hasClippingMask": false,
  "horizontalSpacing": 0,
  "isFixedToViewport": false,
  "isFlippedHorizontal": false,
  "isFlippedVertical": false,
  "isLocked": false,
  "isVisible": true,
  "layerListExpandedType": 0,
  "name": "Booking",
  "nameIsFixed": false,
  "overrideValues": [
  ],
  "resizingConstraint": 63,
  "resizingType": 0,
  "rotation": 0,
  "scale": 1,
  "shouldBreakMaskChain": false,
  "style": {
    "_class": "style",
    "do_objectID": "71692B51-3D62-4921-9EA9-82BF4F7E87DB",
    "endMarkerType": 0,
    "miterLimit": 10,
    "startMarkerType": 0,
    "windingRule": 1
  },
  "symbolID": "3FD581B8-EACE-4A93-A651-81ADD5A8951A",
  "verticalSpacing": 0
}