{
  "_class": "group",
  "booleanOperation": -1,
  "clippingMaskMode": 0,
  "do_objectID": "5C4883D8-3063-464F-A0A1-69CBD1B5264F",
  "exportOptions": {
    "_class": "exportOptions",
    "do_objectID": "CD667147-971D-47E1-86E7-2DB5D69DD9AB",
    "exportFormats": [
    ],
    "includedLayerIds": [
    ],
    "layerOptions": 0,
    "shouldTrim": false
  },
  "frame": {
    "_class": "rect",
    "constrainProportions": false,
    "do_objectID": "F51156D5-61FC-496E-9C53-7B4FCC75A06A",
    "height": 16,
    "width": 183,
    "x": 40,
    "y": 85
  },
  "groupLayout": {
    "_class": "MSImmutableFreeformGroupLayout",
    "do_objectID": "0CDB91EC-18AA-466C-A6A7-9C6EA8601857"
  },
  "hasClickThrough": false,
  "hasClippingMask": false,
  "isFixedToViewport": false,
  "isFlippedHorizontal": false,
  "isFlippedVertical": false,
  "isLocked": false,
  "isVisible": true,
  "layerListExpandedType": 0,
  "layers": [
    {
      "class": "text",
      "id": "E74C9ED5-FF9D-45EF-B1E3-79B6DB138CF1"
    },
    {
      "class": "text",
      "id": "0810FA5E-3877-4D19-B4D1-2AC9A0495669"
    }
  ],
  "name": "Group",
  "nameIsFixed": false,
  "resizingConstraint": 63,
  "resizingType": 0,
  "rotation": 0,
  "shouldBreakMaskChain": false,
  "style": {
    "_class": "style",
    "do_objectID": "306908E8-A319-4E24-90BC-521CDF6BBF7A",
    "endMarkerType": 0,
    "miterLimit": 10,
    "startMarkerType": 0,
    "windingRule": 1
  }
}