{
  "_class": "group",
  "booleanOperation": -1,
  "clippingMaskMode": 0,
  "do_objectID": "EFD3C54E-DBCF-4A35-801B-4826B017F3CD",
  "exportOptions": {
    "_class": "exportOptions",
    "do_objectID": "F7C4BC2C-15B9-42DF-A879-EEC2304538B2",
    "exportFormats": [
    ],
    "includedLayerIds": [
    ],
    "layerOptions": 0,
    "shouldTrim": false
  },
  "frame": {
    "_class": "rect",
    "constrainProportions": false,
    "do_objectID": "B261F4F3-0CD4-4672-9921-FBDEB8B555AF",
    "height": 9.999999999999996,
    "width": 10,
    "x": 7,
    "y": 9.999999999999996
  },
  "groupLayout": {
    "_class": "MSImmutableFreeformGroupLayout",
    "do_objectID": "EBD50A8D-6901-492A-BA39-20E943FBE7B1"
  },
  "hasClickThrough": false,
  "hasClippingMask": false,
  "isFixedToViewport": false,
  "isFlippedHorizontal": false,
  "isFlippedVertical": false,
  "isLocked": false,
  "isVisible": true,
  "layerListExpandedType": 1,
  "layers": [
    {
      "class": "shapePath",
      "id": "45D5E1A8-F133-4855-927A-3E5146E5DE4B"
    }
  ],
  "name": "baseline-add-24px (1)",
  "nameIsFixed": false,
  "resizingConstraint": 63,
  "resizingType": 0,
  "rotation": 0,
  "shouldBreakMaskChain": false,
  "style": {
    "_class": "style",
    "do_objectID": "46701F04-6CAD-4364-9666-C83A6B7F0A41",
    "endMarkerType": 0,
    "miterLimit": 10,
    "startMarkerType": 0,
    "windingRule": 1
  }
}