{
  "_class": "text",
  "attributedString": {
    "_class": "attributedString",
    "attributes": [
      {
        "_class": "stringAttribute",
        "attributes": {
          "MSAttributedStringColorAttribute": {
            "_class": "color",
            "alpha": 1,
            "blue": 0.1176470588235294,
            "green": 0.1176470588235294,
            "red": 0.1176470588235294
          },
          "MSAttributedStringFontAttribute": {
            "_class": "UIFontDescriptor",
            "attributes": {
              "name": "Rajdhani-Medium",
              "size": 16
            }
          },
          "kerning": 0,
          "paragraphStyle": {
            "_class": "paragraphStyle",
            "alignment": 0
          },
          "textStyleVerticalAlignmentKey": 0
        },
        "length": 4,
        "location": 0
      }
    ],
    "string": "Mode"
  },
  "automaticallyDrawOnUnderlyingPath": false,
  "booleanOperation": -1,
  "clippingMaskMode": 0,
  "do_objectID": "077C790A-8FE3-46B9-BA1C-D24FD03561D6",
  "dontSynchroniseWithSymbol": false,
  "exportOptions": {
    "_class": "exportOptions",
    "do_objectID": "2AE8B656-2F3A-4F9E-A2CE-47724F3B300F",
    "exportFormats": [
    ],
    "includedLayerIds": [
    ],
    "layerOptions": 0,
    "shouldTrim": false
  },
  "frame": {
    "_class": "rect",
    "constrainProportions": false,
    "do_objectID": "CA066C84-6D75-4F17-ACFB-6AA9E8E117CB",
    "height": 21,
    "width": 36,
    "x": 0,
    "y": 0
  },
  "glyphBounds": "{{1, 3}, {34, 12}}",
  "hasClippingMask": false,
  "isFixedToViewport": false,
  "isFlippedHorizontal": false,
  "isFlippedVertical": false,
  "isLocked": false,
  "isVisible": true,
  "layerListExpandedType": 0,
  "lineSpacingBehaviour": 2,
  "name": "Mode",
  "nameIsFixed": false,
  "resizingConstraint": 47,
  "resizingType": 0,
  "rotation": 0,
  "shouldBreakMaskChain": false,
  "style": {
    "_class": "style",
    "do_objectID": "8A23862F-A0E1-4A09-A6FA-961EFE647AF7",
    "endMarkerType": 0,
    "miterLimit": 10,
    "startMarkerType": 0,
    "textStyle": {
      "_class": "textStyle",
      "do_objectID": "21DBAC4C-CACB-4E29-8FE2-E25C48C37141",
      "encodedAttributes": {
        "MSAttributedStringColorAttribute": {
          "_class": "color",
          "alpha": 1,
          "blue": 0.1176470588235294,
          "green": 0.1176470588235294,
          "red": 0.1176470588235294
        },
        "MSAttributedStringFontAttribute": {
          "_class": "UIFontDescriptor",
          "attributes": {
            "name": "Rajdhani-Medium",
            "size": 16
          }
        },
        "kerning": 0,
        "paragraphStyle": {
          "_class": "paragraphStyle",
          "alignment": 0
        },
        "textStyleVerticalAlignmentKey": 0
      },
      "verticalAlignment": 0
    },
    "windingRule": 1
  },
  "textBehaviour": 0
}