{
  "_class": "group",
  "booleanOperation": -1,
  "clippingMaskMode": 0,
  "do_objectID": "D4972C91-EE3F-4681-8CFF-7967E9BC6844",
  "exportOptions": {
    "_class": "exportOptions",
    "do_objectID": "B30E572A-2E1B-45E5-9652-82C5A4CAD2EF",
    "exportFormats": [
    ],
    "includedLayerIds": [
    ],
    "layerOptions": 0,
    "shouldTrim": false
  },
  "frame": {
    "_class": "rect",
    "constrainProportions": false,
    "do_objectID": "4F948947-4F9E-425C-BAB0-AA547D1D9832",
    "height": 224,
    "width": 482,
    "x": 50,
    "y": 802
  },
  "groupLayout": {
    "_class": "MSImmutableFreeformGroupLayout",
    "do_objectID": "D4E7688A-EFA1-42DE-A8D3-3B02F33A0FC5"
  },
  "hasClickThrough": false,
  "hasClippingMask": false,
  "isFixedToViewport": false,
  "isFlippedHorizontal": false,
  "isFlippedVertical": false,
  "isLocked": false,
  "isVisible": true,
  "layerListExpandedType": 0,
  "layers": [
    {
      "class": "group",
      "id": "95971FE6-BC69-43C8-AC1E-63FEAD927D68"
    },
    {
      "class": "rectangle",
      "id": "334A43BE-ACEC-45E5-9823-5C4284CFC27C"
    },
    {
      "class": "text",
      "id": "CEC5440C-A8E5-46DC-A8B8-F17F59ABBEC7"
    },
    {
      "class": "text",
      "id": "4FCC1371-07C8-4158-BC92-8D7F88266825"
    },
    {
      "class": "text",
      "id": "826C0CAB-45EE-4E81-BE91-BAD79C3E3E75"
    },
    {
      "class": "text",
      "id": "BE4B8124-F0C6-4FB3-B2E6-7169B6C55B1E"
    }
  ],
  "name": "Group 7",
  "nameIsFixed": false,
  "resizingConstraint": 63,
  "resizingType": 0,
  "rotation": 0,
  "shouldBreakMaskChain": false,
  "style": {
    "_class": "style",
    "borderOptions": {
      "_class": "borderOptions",
      "dashPattern": [
      ],
      "do_objectID": "D6C4CE69-79C8-4A0D-834D-2EF3BCEA0B95",
      "isEnabled": true,
      "lineCapStyle": 0,
      "lineJoinStyle": 0
    },
    "do_objectID": "B49DC67F-5238-4B07-A50F-DCA7585330DF",
    "endMarkerType": 0,
    "miterLimit": 10,
    "startMarkerType": 0,
    "windingRule": 1
  }
}