{
  "_class": "shapeGroup",
  "booleanOperation": -1,
  "clippingMaskMode": 0,
  "do_objectID": "B031B417-DE88-45EA-A150-60C915BC122C",
  "exportOptions": {
    "_class": "exportOptions",
    "do_objectID": "9A87550A-B345-44CF-B0DC-F57AA347986D",
    "exportFormats": [
    ],
    "includedLayerIds": [
    ],
    "layerOptions": 0,
    "shouldTrim": false
  },
  "frame": {
    "_class": "rect",
    "constrainProportions": false,
    "do_objectID": "3BD26848-85E3-4DDC-9DDB-6CDD635C30F4",
    "height": 30.11965217391304,
    "width": 29.00027916730482,
    "x": -0.000378260869564336,
    "y": -0.0008826086956501168
  },
  "groupLayout": {
    "_class": "MSImmutableFreeformGroupLayout",
    "do_objectID": "C3748B48-A8A2-4523-BD89-8867AC59721F"
  },
  "hasClickThrough": false,
  "hasClippingMask": false,
  "isFixedToViewport": false,
  "isFlippedHorizontal": false,
  "isFlippedVertical": false,
  "isLocked": false,
  "isVisible": true,
  "layerListExpandedType": 1,
  "layers": [
    {
      "class": "shapePath",
      "id": "BFD6D0A3-72B1-4BA0-B7A7-77DF4FFBA721"
    },
    {
      "class": "shapePath",
      "id": "D0DE9058-D518-4238-9373-1BCAB3E70767"
    }
  ],
  "name": "Fill 1",
  "nameIsFixed": false,
  "resizingConstraint": 63,
  "resizingType": 0,
  "rotation": 0,
  "shouldBreakMaskChain": false,
  "style": {
    "_class": "style",
    "do_objectID": "7B310824-3FEC-482B-95B9-D81B63A8260F",
    "endMarkerType": 0,
    "fills": [
      {
        "_class": "fill",
        "color": {
          "_class": "color",
          "alpha": 1,
          "blue": 0.6000000000000001,
          "green": 0.6000000000000001,
          "red": 0.6000000000000001
        },
        "fillType": 0,
        "isEnabled": true,
        "noiseIndex": 0,
        "noiseIntensity": 0,
        "patternFillType": 1,
        "patternTileScale": 1
      }
    ],
    "miterLimit": 10,
    "startMarkerType": 0,
    "windingRule": 1
  },
  "windingRule": 1
}