{
  "_class": "group",
  "booleanOperation": -1,
  "clippingMaskMode": 0,
  "do_objectID": "DF217768-9D7C-42A3-AB96-4E82DF573FC8",
  "exportOptions": {
    "_class": "exportOptions",
    "do_objectID": "37F277DE-AE6D-4C4E-B786-4015FBF88ED9",
    "exportFormats": [
    ],
    "includedLayerIds": [
    ],
    "layerOptions": 0,
    "shouldTrim": false
  },
  "frame": {
    "_class": "rect",
    "constrainProportions": false,
    "do_objectID": "22284901-DCBB-44CC-94F0-9C1871BBF842",
    "height": 21,
    "width": 75,
    "x": 900,
    "y": 230
  },
  "groupLayout": {
    "_class": "MSImmutableFreeformGroupLayout",
    "do_objectID": "A0C6224A-A34E-4AF8-A3EF-F1A2BDBDAE0A"
  },
  "hasClickThrough": false,
  "hasClippingMask": false,
  "isFixedToViewport": false,
  "isFlippedHorizontal": false,
  "isFlippedVertical": false,
  "isLocked": false,
  "isVisible": true,
  "layerListExpandedType": 2,
  "layers": [
    {
      "class": "text",
      "id": "20CEABF6-F138-47E3-9AD0-E9318844D27C"
    }
  ],
  "name": "Link Copy",
  "nameIsFixed": true,
  "resizingConstraint": 63,
  "resizingType": 0,
  "rotation": 0,
  "shouldBreakMaskChain": false,
  "style": {
    "_class": "style",
    "do_objectID": "894E280C-5CDC-4C92-975D-E788474C3E1F",
    "endMarkerType": 0,
    "miterLimit": 10,
    "startMarkerType": 0,
    "windingRule": 1
  }
}