{
  "_class": "group",
  "booleanOperation": -1,
  "clippingMaskMode": 0,
  "do_objectID": "6A7FD347-7148-4FBA-98DF-0F571A9B1941",
  "exportOptions": {
    "_class": "exportOptions",
    "do_objectID": "940E06C1-2E92-47FA-9256-D89DD4415748",
    "exportFormats": [
    ],
    "includedLayerIds": [
    ],
    "layerOptions": 0,
    "shouldTrim": false
  },
  "frame": {
    "_class": "rect",
    "constrainProportions": true,
    "do_objectID": "1DD5E393-2D21-4CD8-923C-FDDC344530C6",
    "height": 30.26086956521739,
    "width": 29,
    "x": 281,
    "y": 6.000000000000052
  },
  "groupLayout": {
    "_class": "MSImmutableFreeformGroupLayout",
    "do_objectID": "B549E704-2BFD-4845-AA65-65EBDB42E6BD"
  },
  "hasClickThrough": false,
  "hasClippingMask": false,
  "isFixedToViewport": false,
  "isFlippedHorizontal": false,
  "isFlippedVertical": false,
  "isLocked": false,
  "isVisible": true,
  "layerListExpandedType": 0,
  "layers": [
    {
      "class": "shapePath",
      "id": "08D20678-593F-4FEF-9E23-3A0922B6F17D"
    },
    {
      "class": "shapeGroup",
      "id": "16C96C90-812F-458A-9E9B-A69832AE51E2"
    }
  ],
  "name": "Group 3",
  "nameIsFixed": false,
  "resizingConstraint": 63,
  "resizingType": 0,
  "rotation": 0,
  "shouldBreakMaskChain": false,
  "style": {
    "_class": "style",
    "do_objectID": "756F8FF2-A262-4CD1-B8A4-548F38D0FF58",
    "endMarkerType": 0,
    "miterLimit": 10,
    "startMarkerType": 0,
    "windingRule": 1
  }
}