{
  "_class": "group",
  "booleanOperation": -1,
  "clippingMaskMode": 0,
  "do_objectID": "DD6C6D69-1A8F-4048-8007-238861C845A0",
  "exportOptions": {
    "_class": "exportOptions",
    "do_objectID": "B768A6B5-F53C-45C5-958F-7C8697B1BF32",
    "exportFormats": [
    ],
    "includedLayerIds": [
    ],
    "layerOptions": 0,
    "shouldTrim": false
  },
  "frame": {
    "_class": "rect",
    "constrainProportions": false,
    "do_objectID": "2BB76019-249F-42EE-8F78-EE41A1D72018",
    "height": 72,
    "width": 548,
    "x": 50,
    "y": 284
  },
  "groupLayout": {
    "_class": "MSImmutableFreeformGroupLayout",
    "do_objectID": "2D1FDF8E-4B47-49BB-A06A-4491A84207E8"
  },
  "hasClickThrough": false,
  "hasClippingMask": false,
  "isFixedToViewport": false,
  "isFlippedHorizontal": false,
  "isFlippedVertical": false,
  "isLocked": false,
  "isVisible": true,
  "layerListExpandedType": 2,
  "layers": [
  ],
  "name": "Group 19 Copy",
  "nameIsFixed": false,
  "resizingConstraint": 63,
  "resizingType": 0,
  "rotation": 0,
  "shouldBreakMaskChain": false,
  "style": {
    "_class": "style",
    "borderOptions": {
      "_class": "borderOptions",
      "dashPattern": [
      ],
      "do_objectID": "4896D851-2BD7-4850-A242-410320161A42",
      "isEnabled": true,
      "lineCapStyle": 0,
      "lineJoinStyle": 0
    },
    "colorControls": {
      "_class": "colorControls",
      "brightness": 0,
      "contrast": 1,
      "do_objectID": "C522A758-ED2E-4C61-A123-A1D5A87E650E",
      "hue": 0,
      "isEnabled": true,
      "saturation": 1
    },
    "do_objectID": "23B3CC26-93D0-4ED0-A5F8-CC122E175938",
    "endMarkerType": 0,
    "miterLimit": 10,
    "startMarkerType": 0,
    "windingRule": 1
  }
}