{
  "_class": "group",
  "booleanOperation": -1,
  "clippingMaskMode": 0,
  "do_objectID": "46B1FB01-0455-4E98-81EC-73E76C566BC8",
  "exportOptions": {
    "_class": "exportOptions",
    "do_objectID": "79564539-7BCD-453A-AA21-BACF5DB2DDC1",
    "exportFormats": [
    ],
    "includedLayerIds": [
    ],
    "layerOptions": 0,
    "shouldTrim": false
  },
  "frame": {
    "_class": "rect",
    "constrainProportions": false,
    "do_objectID": "51204EA7-386C-48E9-A932-1B35E1D8ACC6",
    "height": 21,
    "width": 280,
    "x": 571,
    "y": 0
  },
  "groupLayout": {
    "_class": "MSImmutableFreeformGroupLayout",
    "do_objectID": "E87F392A-EF9C-447C-9221-C9174416694B"
  },
  "hasClickThrough": false,
  "hasClippingMask": false,
  "isFixedToViewport": false,
  "isFlippedHorizontal": false,
  "isFlippedVertical": false,
  "isLocked": false,
  "isVisible": true,
  "layerListExpandedType": 1,
  "layers": [
    {
      "class": "text",
      "id": "DEAC5927-A09E-4E9C-9D71-1AA07540BDA7"
    },
    {
      "class": "text",
      "id": "F3847685-812B-4DBB-BE04-0C2F1F957751"
    }
  ],
  "name": "Group 18",
  "nameIsFixed": false,
  "resizingConstraint": 63,
  "resizingType": 0,
  "rotation": 0,
  "shouldBreakMaskChain": false,
  "style": {
    "_class": "style",
    "borderOptions": {
      "_class": "borderOptions",
      "dashPattern": [
      ],
      "do_objectID": "07DA260C-6AAE-48A3-8B06-3D713D2B92FC",
      "isEnabled": true,
      "lineCapStyle": 0,
      "lineJoinStyle": 0
    },
    "colorControls": {
      "_class": "colorControls",
      "brightness": 0,
      "contrast": 1,
      "do_objectID": "83AC1771-0A24-47B3-8FFF-776FB8D4BB6A",
      "hue": 0,
      "isEnabled": true,
      "saturation": 1
    },
    "do_objectID": "80AFC886-5A92-4AB5-9FF0-8C269DF91EAA",
    "endMarkerType": 0,
    "miterLimit": 10,
    "startMarkerType": 0,
    "windingRule": 1
  }
}