{
  "_class": "group",
  "booleanOperation": -1,
  "clippingMaskMode": 0,
  "do_objectID": "E1C0FB0F-E169-4957-A98D-5D14901FDC38",
  "exportOptions": {
    "_class": "exportOptions",
    "do_objectID": "31EE61C2-D92E-49C9-BA1B-3A0D2BC13827",
    "exportFormats": [
    ],
    "includedLayerIds": [
    ],
    "layerOptions": 0,
    "shouldTrim": false
  },
  "frame": {
    "_class": "rect",
    "constrainProportions": false,
    "do_objectID": "5EF10643-0315-40B1-8C54-B03D4D84349B",
    "height": 317,
    "width": 25,
    "x": 13,
    "y": 121
  },
  "groupLayout": {
    "_class": "MSImmutableFreeformGroupLayout",
    "do_objectID": "BB6F9C33-ADAC-4CCB-96CA-3EAEF8D99B07"
  },
  "hasClickThrough": false,
  "hasClippingMask": false,
  "isFixedToViewport": false,
  "isFlippedHorizontal": false,
  "isFlippedVertical": false,
  "isLocked": false,
  "isVisible": true,
  "layerListExpandedType": 0,
  "layers": [
    {
      "class": "symbolInstance",
      "id": "B2AB2676-9F6C-4F9C-B850-F5480912CEAB"
    },
    {
      "class": "symbolInstance",
      "id": "00E2BE87-44A4-4FD9-ABF2-7B449668D74E"
    },
    {
      "class": "symbolInstance",
      "id": "231F7C82-424D-4B44-A1F2-EEAC5E1B1F6A"
    },
    {
      "class": "symbolInstance",
      "id": "EDE6F958-8960-488B-9FF3-7F2FB4D522A5"
    },
    {
      "class": "symbolInstance",
      "id": "E0E272F6-B5B3-45C7-A6AD-7598EE802D96"
    },
    {
      "class": "symbolInstance",
      "id": "AF5CA209-63F0-4107-9821-AC0A39EC8A45"
    },
    {
      "class": "group",
      "id": "BB048661-F65A-46E5-85DD-EB83E9860095"
    }
  ],
  "name": "Group 23",
  "nameIsFixed": false,
  "resizingConstraint": 63,
  "resizingType": 0,
  "rotation": 0,
  "shouldBreakMaskChain": false,
  "style": {
    "_class": "style",
    "do_objectID": "748F3723-DC4D-4E55-A59A-C2C2D4F47D19",
    "endMarkerType": 0,
    "miterLimit": 10,
    "startMarkerType": 0,
    "windingRule": 1
  }
}