{
  "_class": "group",
  "booleanOperation": -1,
  "clippingMaskMode": 0,
  "do_objectID": "F4AE5264-4C44-4CE9-B162-3C121500DF65",
  "exportOptions": {
    "_class": "exportOptions",
    "do_objectID": "1DF43948-4761-46D5-B337-C5D011638981",
    "exportFormats": [
    ],
    "includedLayerIds": [
    ],
    "layerOptions": 0,
    "shouldTrim": false
  },
  "frame": {
    "_class": "rect",
    "constrainProportions": false,
    "do_objectID": "23126F6D-5BA9-4FF6-905E-C840CEAD1698",
    "height": 35,
    "width": 114,
    "x": 1049,
    "y": 39
  },
  "groupLayout": {
    "_class": "MSImmutableFreeformGroupLayout",
    "do_objectID": "6F35B4A3-664B-4026-B5A6-8AB3A7C574DC"
  },
  "hasClickThrough": false,
  "hasClippingMask": false,
  "isFixedToViewport": false,
  "isFlippedHorizontal": false,
  "isFlippedVertical": false,
  "isLocked": false,
  "isVisible": true,
  "layerListExpandedType": 1,
  "layers": [
    {
      "class": "shapePath",
      "id": "E27C412D-D9B3-48DE-93DC-2A18610936E9"
    },
    {
      "class": "text",
      "id": "C55A9DF9-A0E8-4777-87EC-4A72431FB033"
    }
  ],
  "name": "btn",
  "nameIsFixed": true,
  "resizingConstraint": 63,
  "resizingType": 0,
  "rotation": 0,
  "shouldBreakMaskChain": false,
  "style": {
    "_class": "style",
    "borderOptions": {
      "_class": "borderOptions",
      "dashPattern": [
      ],
      "do_objectID": "F8B7842E-9ECC-45EA-A8FD-688CAF5CEC4C",
      "isEnabled": true,
      "lineCapStyle": 0,
      "lineJoinStyle": 0
    },
    "colorControls": {
      "_class": "colorControls",
      "brightness": 0,
      "contrast": 1,
      "do_objectID": "B15138FB-62B7-4A39-B31B-88008276F011",
      "hue": 0,
      "isEnabled": true,
      "saturation": 1
    },
    "do_objectID": "04805592-080A-4C7D-B4BF-0B4BF8F412E4",
    "endMarkerType": 0,
    "miterLimit": 10,
    "startMarkerType": 0,
    "windingRule": 1
  }
}