{
  "_class": "text",
  "attributedString": {
    "_class": "attributedString",
    "attributes": [
      {
        "_class": "stringAttribute",
        "attributes": {
          "MSAttributedStringColorAttribute": {
            "_class": "color",
            "alpha": 1,
            "blue": 0.615686274509804,
            "green": 0.615686274509804,
            "red": 0.615686274509804
          },
          "MSAttributedStringFontAttribute": {
            "_class": "UIFontDescriptor",
            "attributes": {
              "name": "LucidaGrande",
              "size": 8
            }
          }
        },
        "length": 1,
        "location": 0
      }
    ],
    "string": "F"
  },
  "automaticallyDrawOnUnderlyingPath": false,
  "booleanOperation": -1,
  "clippingMaskMode": 0,
  "do_objectID": "69968DAA-F4D9-497D-BA3A-62FA426587D6",
  "dontSynchroniseWithSymbol": false,
  "exportOptions": {
    "_class": "exportOptions",
    "do_objectID": "69AC7E39-00E6-4E6D-89AC-15704FFA72CD",
    "exportFormats": [
    ],
    "includedLayerIds": [
    ],
    "layerOptions": 0,
    "shouldTrim": false
  },
  "frame": {
    "_class": "rect",
    "constrainProportions": false,
    "do_objectID": "C5886ABD-D645-41BE-9F6A-7E2E9FF1F72B",
    "height": 10,
    "width": 5,
    "x": 115.896303,
    "y": 89.578125
  },
  "glyphBounds": "{{0, 2}, {4, 6}}",
  "hasClippingMask": false,
  "isFixedToViewport": false,
  "isFlippedHorizontal": false,
  "isFlippedVertical": false,
  "isLocked": false,
  "isVisible": true,
  "layerListExpandedType": 0,
  "lineSpacingBehaviour": 1,
  "name": "F",
  "nameIsFixed": false,
  "resizingConstraint": 47,
  "resizingType": 0,
  "rotation": 0,
  "shouldBreakMaskChain": false,
  "style": {
    "_class": "style",
    "borderOptions": {
      "_class": "borderOptions",
      "dashPattern": [
      ],
      "do_objectID": "8D95A0D1-6581-4A86-996F-B0A50AAC6B6E",
      "isEnabled": true,
      "lineCapStyle": 0,
      "lineJoinStyle": 0
    },
    "colorControls": {
      "_class": "colorControls",
      "brightness": 0,
      "contrast": 1,
      "do_objectID": "12C08FC5-2D73-42A7-92DD-F94B0D4F81B4",
      "hue": 0,
      "isEnabled": true,
      "saturation": 1
    },
    "do_objectID": "506FB6F7-6249-49F6-A4D7-8CA05E0503AD",
    "endMarkerType": 0,
    "miterLimit": 10,
    "startMarkerType": 0,
    "textStyle": {
      "_class": "textStyle",
      "do_objectID": "274FFC2C-92A9-461A-BA87-C4E1AB428595",
      "encodedAttributes": {
        "MSAttributedStringColorAttribute": {
          "_class": "color",
          "alpha": 1,
          "blue": 0.615686274509804,
          "green": 0.615686274509804,
          "red": 0.615686274509804
        },
        "MSAttributedStringFontAttribute": {
          "_class": "UIFontDescriptor",
          "attributes": {
            "name": "LucidaGrande",
            "size": 8
          }
        }
      },
      "verticalAlignment": 0
    },
    "windingRule": 1
  },
  "textBehaviour": 0
}