{
  "_class": "group",
  "booleanOperation": -1,
  "clippingMaskMode": 0,
  "do_objectID": "610177CD-871B-4607-88F0-7A0755AFB487",
  "exportOptions": {
    "_class": "exportOptions",
    "do_objectID": "5567692E-4CFE-4828-B053-65CBF629C9B1",
    "exportFormats": [
    ],
    "includedLayerIds": [
    ],
    "layerOptions": 0,
    "shouldTrim": false
  },
  "frame": {
    "_class": "rect",
    "constrainProportions": false,
    "do_objectID": "4B4704D4-5D7B-41E7-B47B-8C1DD56E857C",
    "height": 174,
    "width": 75,
    "x": 715,
    "y": 1355
  },
  "groupLayout": {
    "_class": "MSImmutableFreeformGroupLayout",
    "do_objectID": "44F5B150-A7C3-4573-A2A8-36E219D39274"
  },
  "hasClickThrough": false,
  "hasClippingMask": false,
  "isFixedToViewport": false,
  "isFlippedHorizontal": false,
  "isFlippedVertical": false,
  "isLocked": false,
  "isVisible": true,
  "layerListExpandedType": 2,
  "layers": [
    {
      "class": "text",
      "id": "CE22D291-F8D3-4B18-B062-B8B047AB266B"
    },
    {
      "class": "text",
      "id": "04941C44-B7A7-4A35-B25E-75F926DAD5D3"
    },
    {
      "class": "text",
      "id": "361BAB34-EE19-42D2-B011-36BF97CB618C"
    },
    {
      "class": "text",
      "id": "B884E8B7-3E72-4202-881C-B88D0464690C"
    }
  ],
  "name": "Group 8",
  "nameIsFixed": false,
  "resizingConstraint": 63,
  "resizingType": 0,
  "rotation": 0,
  "shouldBreakMaskChain": false,
  "style": {
    "_class": "style",
    "do_objectID": "5A742A8B-8554-47AF-AF3A-6261894EB5DC",
    "endMarkerType": 0,
    "miterLimit": 10,
    "startMarkerType": 0,
    "windingRule": 1
  }
}