{
  "_class": "group",
  "booleanOperation": -1,
  "clippingMaskMode": 0,
  "do_objectID": "D81C0AB7-CB62-48EE-81DD-905621FDF04F",
  "exportOptions": {
    "_class": "exportOptions",
    "do_objectID": "7DCF2D7C-1A88-4B12-9F89-14E2DA686731",
    "exportFormats": [
      {
        "_class": "exportFormat",
        "absoluteSize": 0,
        "fileFormat": "png",
        "name": "",
        "namingScheme": 0,
        "scale": 1,
        "visibleScaleType": 0
      }
    ],
    "includedLayerIds": [
    ],
    "layerOptions": 0,
    "shouldTrim": false
  },
  "frame": {
    "_class": "rect",
    "constrainProportions": false,
    "do_objectID": "6050BA0E-4E80-4358-8EDB-85C5EABB4287",
    "height": 34,
    "width": 35,
    "x": 137,
    "y": 0
  },
  "groupLayout": {
    "_class": "MSImmutableFreeformGroupLayout",
    "do_objectID": "3623CA16-0B70-4EBF-89FA-70AC4B77FA55"
  },
  "hasClickThrough": false,
  "hasClippingMask": false,
  "isFixedToViewport": false,
  "isFlippedHorizontal": false,
  "isFlippedVertical": false,
  "isLocked": false,
  "isVisible": true,
  "layerListExpandedType": 2,
  "layers": [
    {
      "class": "group",
      "id": "8CB09C33-72BA-464A-971D-37307DD692A7"
    },
    {
      "class": "text",
      "id": "1B643EF7-6768-4D65-9CC3-9EC5C14938F1"
    }
  ],
  "name": "Group 11",
  "nameIsFixed": false,
  "resizingConstraint": 63,
  "resizingType": 0,
  "rotation": 0,
  "shouldBreakMaskChain": false,
  "style": {
    "_class": "style",
    "do_objectID": "346E7527-80EA-4FD1-B041-EEC6C3F039DB",
    "endMarkerType": 0,
    "miterLimit": 10,
    "startMarkerType": 0,
    "windingRule": 1
  }
}