{
  "_class": "text",
  "attributedString": {
    "_class": "attributedString",
    "attributes": [
      {
        "_class": "stringAttribute",
        "attributes": {
          "MSAttributedStringColorAttribute": {
            "_class": "color",
            "alpha": 1,
            "blue": 0.6039215686274509,
            "green": 0.6039215686274509,
            "red": 0.6039215686274509
          },
          "MSAttributedStringFontAttribute": {
            "_class": "fontDescriptor",
            "attributes": {
              "name": "LucidaGrande",
              "size": 7.0712
            }
          },
          "kerning": -0.028
        },
        "length": 1,
        "location": 0
      },
      {
        "_class": "stringAttribute",
        "attributes": {
          "MSAttributedStringColorAttribute": {
            "_class": "color",
            "alpha": 1,
            "blue": 0.6039215686274509,
            "green": 0.6039215686274509,
            "red": 0.6039215686274509
          },
          "MSAttributedStringFontAttribute": {
            "_class": "fontDescriptor",
            "attributes": {
              "name": "LucidaGrande",
              "size": 7.0712
            }
          },
          "kerning": 0.1609388
        },
        "length": 1,
        "location": 1
      },
      {
        "_class": "stringAttribute",
        "attributes": {
          "MSAttributedStringColorAttribute": {
            "_class": "color",
            "alpha": 1,
            "blue": 0.6039215686274509,
            "green": 0.6039215686274509,
            "red": 0.6039215686274509
          },
          "MSAttributedStringFontAttribute": {
            "_class": "fontDescriptor",
            "attributes": {
              "name": "LucidaGrande",
              "size": 7.0712
            }
          },
          "kerning": -0.028
        },
        "length": 1,
        "location": 2
      }
    ],
    "string": "AUG"
  },
  "automaticallyDrawOnUnderlyingPath": false,
  "booleanOperation": -1,
  "clippingMaskMode": 0,
  "do_objectID": "294BB555-7474-4417-A373-0994FDC96ACE",
  "dontSynchroniseWithSymbol": false,
  "exportOptions": {
    "_class": "exportOptions",
    "do_objectID": "B7139DC4-8DBA-4467-8B42-ACC7936E3ABC",
    "exportFormats": [
    ],
    "includedLayerIds": [
    ],
    "layerOptions": 0,
    "shouldTrim": false
  },
  "frame": {
    "_class": "rect",
    "constrainProportions": false,
    "do_objectID": "15D36C37-9C56-4FE2-B780-C6ADA3DF74E0",
    "height": 8,
    "width": 17.66066838046277,
    "x": 281.2159383033395,
    "y": 129.086956521739
  },
  "glyphBounds": "{{0, 1}, {15, 7}}",
  "hasClippingMask": false,
  "isFixedToViewport": false,
  "isFlippedHorizontal": false,
  "isFlippedVertical": false,
  "isLocked": false,
  "isVisible": true,
  "layerListExpandedType": 0,
  "lineSpacingBehaviour": 1,
  "name": "AUG",
  "nameIsFixed": false,
  "resizingConstraint": 47,
  "resizingType": 0,
  "rotation": 0,
  "shouldBreakMaskChain": false,
  "style": {
    "_class": "style",
    "borderOptions": {
      "_class": "borderOptions",
      "dashPattern": [
      ],
      "do_objectID": "EDE5E029-A78A-4F89-B822-44C9F59F73AE",
      "isEnabled": true,
      "lineCapStyle": 0,
      "lineJoinStyle": 0
    },
    "colorControls": {
      "_class": "colorControls",
      "brightness": 0,
      "contrast": 1,
      "do_objectID": "ED03D85F-896C-4B06-B687-405810756181",
      "hue": 0,
      "isEnabled": true,
      "saturation": 1
    },
    "do_objectID": "9FDA01C8-638A-4610-B72B-91F91DD4531E",
    "endMarkerType": 0,
    "miterLimit": 10,
    "startMarkerType": 0,
    "textStyle": {
      "_class": "textStyle",
      "do_objectID": "C4C0A8E5-C7AC-4426-9F97-F429157789D2",
      "encodedAttributes": {
        "MSAttributedStringColorAttribute": {
          "_class": "color",
          "alpha": 1,
          "blue": 0.6039215686274509,
          "green": 0.6039215686274509,
          "red": 0.6039215686274509
        },
        "MSAttributedStringFontAttribute": {
          "_class": "fontDescriptor",
          "attributes": {
            "name": "LucidaGrande",
            "size": 7.0712
          }
        },
        "kerning": -0.028
      },
      "verticalAlignment": 0
    },
    "windingRule": 1
  },
  "textBehaviour": 1
}