{
  "_class": "group",
  "booleanOperation": -1,
  "clippingMaskMode": 0,
  "do_objectID": "6DD52999-1986-484F-B113-FF92E81207E8",
  "exportOptions": {
    "_class": "exportOptions",
    "do_objectID": "FB3EA265-F70B-49D5-B374-FC649FD41CDB",
    "exportFormats": [
    ],
    "includedLayerIds": [
    ],
    "layerOptions": 0,
    "shouldTrim": false
  },
  "frame": {
    "_class": "rect",
    "constrainProportions": false,
    "do_objectID": "32548FA8-E291-4947-A1F3-B12AC73C01AC",
    "height": 9,
    "width": 16,
    "x": 1239,
    "y": 615
  },
  "groupLayout": {
    "_class": "MSImmutableFreeformGroupLayout",
    "do_objectID": "46BD6E18-A8CD-47A3-85B2-BA132E5E9030"
  },
  "hasClickThrough": false,
  "hasClippingMask": false,
  "isFixedToViewport": false,
  "isFlippedHorizontal": false,
  "isFlippedVertical": false,
  "isLocked": false,
  "isVisible": true,
  "layerListExpandedType": 2,
  "layers": [
    {
      "class": "shapeGroup",
      "id": "630229A0-9882-49B8-8EE7-29D9A7FD9611"
    },
    {
      "class": "shapePath",
      "id": "4129A152-1837-4A45-BD0D-4A9EE1D4E3B9"
    },
    {
      "class": "shapeGroup",
      "id": "FC244A37-A4C8-4E57-A0EA-0F745D5C31FC"
    }
  ],
  "name": "view (3) copy 3",
  "nameIsFixed": false,
  "resizingConstraint": 63,
  "resizingType": 0,
  "rotation": 0,
  "shouldBreakMaskChain": false,
  "style": {
    "_class": "style",
    "do_objectID": "D7B807B9-88E8-45C2-82D2-2138AC0EEFC9",
    "endMarkerType": 0,
    "miterLimit": 10,
    "startMarkerType": 0,
    "windingRule": 1
  }
}